e2b_code_interpreter/__init__.py
e2b_code_interpreter/charts.py
e2b_code_interpreter/code_interpreter_async.py
e2b_code_interpreter/code_interpreter_sync.py
e2b_code_interpreter/constants.py
e2b_code_interpreter/exceptions.py
e2b_code_interpreter/models.py
e2b_code_interpreter-2.2.0.dist-info/LICENSE
e2b_code_interpreter-2.2.0.dist-info/METADATA
e2b_code_interpreter-2.2.0.dist-info/WHEEL
e2b_code_interpreter-2.2.0.dist-info/RECORD
