Metadata-Version: 2.1
Name: e2b-code-interpreter
Version: 2.2.0
Summary: E2B Code Interpreter - Stateful code execution
Home-page: https://e2b.dev/
License: MIT
Author: e2b
Author-email: hello@e2b.dev
Requires-Python: >=3.9,<4.0
Classifier: License :: OSI Approved :: MIT License
Classifier: Programming Language :: Python :: 3
Classifier: Programming Language :: Python :: 3.9
Classifier: Programming Language :: Python :: 3.10
Classifier: Programming Language :: Python :: 3.11
Classifier: Programming Language :: Python :: 3.12
Requires-Dist: attrs (>=21.3.0)
Requires-Dist: e2b (>=2.3.0,<3.0.0)
Requires-Dist: httpx (>=0.20.0,<1.0.0)
Project-URL: Bug Tracker, https://github.com/e2b-dev/code-interpreter/issues
Project-URL: Repository, https://github.com/e2b-dev/code-interpreter/tree/main/python
